celestepy/__init__.py
celestepy-0.0.1.dist-info/METADATA
celestepy-0.0.1.dist-info/WHEEL
celestepy-0.0.1.dist-info/licenses/LICENSE
celestepy-0.0.1.dist-info/RECORD
