Metadata-Version: 2.4
Name: celestepy
Version: 0.0.1
Summary: Celeste AI Framework - Placeholder package (use celeste-ai instead)
Project-URL: Homepage, https://celeste-ai.co
Project-URL: Repository, https://github.com/celeste-kai/celeste-ai
Author-email: agent-kai <kai@celeste-ai.co>
License-File: LICENSE
Keywords: ai,anthropic,celeste,google,ml,multimodal,openai
Classifier: Development Status :: 1 - Planning
Classifier: Intended Audience :: Developers
Classifier: License :: OSI Approved :: MIT License
Classifier: Programming Language :: Python :: 3
Classifier: Programming Language :: Python :: 3.9
Classifier: Programming Language :: Python :: 3.10
Classifier: Programming Language :: Python :: 3.11
Classifier: Programming Language :: Python :: 3.12
Classifier: Programming Language :: Python :: 3.13
Classifier: Topic :: Scientific/Engineering :: Artificial Intelligence
Requires-Python: >=3.9
